notte_llm/__init__.py
notte_llm/engine.py
notte_llm/logging.py
notte_llm/prompt.py
notte_llm/py.typed
notte_llm/service.py
notte_llm/tracer.py
notte_llm/types.py
notte_llm/config/endpoints.csv
notte_llm/prompts/action-listing/anthropic/user.md
notte_llm/prompts/action-listing/optim/user.md
notte_llm/prompts/action-listing/simple/user.md
notte_llm/prompts/action-listing-incr/user.md
notte_llm/prompts/action-selection/system.md
notte_llm/prompts/action-selection/user.md
notte_llm/prompts/data-extraction/user.md
notte_llm/prompts/data-extraction/all_data/user.md
notte_llm/prompts/data-extraction/only_main_content/user.md
notte_llm/prompts/data-extraction/two_sections/user.md
notte_llm/prompts/debug-failing-action-exec/user.md
notte_llm/prompts/document-category/base/user.md
notte_llm/prompts/document-category/optim/user.md
notte_llm/prompts/extract-json-schema/multi-entity/system.md
notte_llm/prompts/extract-json-schema/multi-entity/user.md
notte_llm/prompts/extract-without-json-schema/system.md
notte_llm/prompts/extract-without-json-schema/user.md
notte_llm/prompts/generate-json-schema/system.md
notte_llm/prompts/generate-json-schema/user.md
notte_llm-1.8.3.dist-info/METADATA
notte_llm-1.8.3.dist-info/WHEEL
notte_llm-1.8.3.dist-info/RECORD
